breachcollection/__init__.py
breachcollection/breachcollection.py
breachcollection-1.0.1.dist-info/licenses/LICENSE
breachcollection-1.0.1.dist-info/METADATA
breachcollection-1.0.1.dist-info/WHEEL
breachcollection-1.0.1.dist-info/top_level.txt
breachcollection-1.0.1.dist-info/RECORD
