Metadata-Version: 2.4
Name: breachcollection
Version: 1.0.1
Summary: A Python3 package that integrates the BreachCollection API.
Author: BreachCollection
Classifier: Programming Language :: Python :: 3
Classifier: License :: OSI Approved :: MIT License
Classifier: Operating System :: OS Independent
Requires-Python: >=3.6
License-File: LICENSE
Requires-Dist: requests
Dynamic: license-file
